sprite_ai/__init__.py
sprite_ai/assistant/__init__.py
sprite_ai/assistant/assistant.py
sprite_ai/assistant/assistant_config.py
sprite_ai/assistant/assistant_factory.py
sprite_ai/assistant/language_config.py
sprite_ai/audio/__init__.py
sprite_ai/audio/sound.py
sprite_ai/audio/speach/__init__.py
sprite_ai/audio/speach/speaker.py
sprite_ai/audio/speach/speaker_factory.py
sprite_ai/audio/transcriber.py
sprite_ai/audio/wakeword_detector.py
sprite_ai/behaviour.py
sprite_ai/constants.py
sprite_ai/controller/chat_window_controller.py
sprite_ai/core/__init__.py
sprite_ai/core/sprite.py
sprite_ai/core/sprite_behaviour.py
sprite_ai/core/sprite_state.py
sprite_ai/default_animations.py
sprite_ai/default_states.py
sprite_ai/event_manager.py
sprite_ai/gui/__init__.py
sprite_ai/gui/sprite_gui.py
sprite_ai/language/__init__.py
sprite_ai/language/chat_message.py
sprite_ai/language/chat_model_factory.py
sprite_ai/language/chat_session.py
sprite_ai/language/chat_state.py
sprite_ai/language/default_model_configs.py
sprite_ai/language/languaga_model_factory.py
sprite_ai/language/language_model.py
sprite_ai/language/language_model_config.py
sprite_ai/language/language_model_server.py
sprite_ai/language/language_model_server_factory.py
sprite_ai/language/llm_factory.py
sprite_ai/main.py
sprite_ai/movement/__init__.py
sprite_ai/movement/boomerang_loop_movement.py
sprite_ai/movement/composed_movement.py
sprite_ai/movement/coordinate.py
sprite_ai/movement/idle_movement.py
sprite_ai/movement/linear_movement.py
sprite_ai/movement/loop_movement.py
sprite_ai/movement/movement.py
sprite_ai/movement/movement_factory.py
sprite_ai/movement/sequence_movement.py
sprite_ai/movement/typing_utils.py
sprite_ai/movement/walking_movement.py
sprite_ai/physics.py
sprite_ai/resources/__init__.py
sprite_ai/resources/default_config copy.yaml
sprite_ai/resources/default_config.yaml
sprite_ai/resources/icons/__init__.py
sprite_ai/resources/icons/carboardbox_open.png
sprite_ai/resources/icons/icon.ico
sprite_ai-2.0.1.dist-info/METADATA
sprite_ai-2.0.1.dist-info/WHEEL
sprite_ai-2.0.1.dist-info/entry_points.txt
sprite_ai-2.0.1.dist-info/RECORD
