Metadata-Version: 2.1
Name: sprite-ai
Version: 2.0.1
Summary: Sprite AI is an AI companion for your desktop
Author: Caio D
Author-email: caiobd@protonmail.com
Requires-Python: >=3.9,<3.12
Classifier: Programming Language :: Python :: 3
Classifier: Programming Language :: Python :: 3.9
Classifier: Programming Language :: Python :: 3.10
Classifier: Programming Language :: Python :: 3.11
Requires-Dist: dbus-python (>=1.3.2,<2.0.0)
Requires-Dist: faster-whisper (>=0.10.0,<0.11.0)
Requires-Dist: langchain (>=0.2.0,<0.3.0)
Requires-Dist: langchain-community (>=0.2.0,<0.3.0)
Requires-Dist: langchain-openai (>=0.1.7,<0.2.0)
Requires-Dist: langchain-together (>=0.1.2,<0.2.0)
Requires-Dist: llama-cpp-python[server] (>=0.2.75,<0.3.0)
Requires-Dist: loguru (>=0.7.2,<0.8.0)
Requires-Dist: openwakeword (>=0.6.0,<0.7.0)
Requires-Dist: piper-tts (>=1.2.0,<2.0.0)
Requires-Dist: platformdirs (>=4.0.0,<5.0.0)
Requires-Dist: plyer (>=2.1.0,<3.0.0)
Requires-Dist: progressbar2 (>=4.2.0,<5.0.0)
Requires-Dist: pyaudio (>=0.2.14,<0.3.0)
Requires-Dist: pydantic (>=2.4.2,<3.0.0)
Requires-Dist: pyqt5 (==5.15.2)
Requires-Dist: pyqtkeybind (>=0.0.9,<0.0.10)
Requires-Dist: pyyaml (>=6.0.1,<7.0.0)
Requires-Dist: sounddevice (>=0.4.6,<0.5.0)
Requires-Dist: soundfile (>=0.12.1,<0.13.0)
Requires-Dist: texteditor (>=1.4.1,<2.0.0)
Requires-Dist: transformers (>=4.37.1,<5.0.0)
Requires-Dist: typer (>=0.9.0,<0.10.0)
